Workbook
Name MODEL_NO: Sheet2!$C$38:$C$43

Sheet Mini 2 200
A1: Technical Data Sheet - Domestic Thermodynamics Solar Heat Pump
A44: WORLDS MOST ADVANCED SOLAR HEAT PUMP TECHNOLOGY
A53: NEXT-GEN THERMODYNAMICS SOLAR HEAT PUMP
A55: Technical Data Sheet - Domestic Thermodynamics Solar Heat Pump
A59: NEXT-GEN THERMODYNAMICS SOLAR HEAT PUMP | E59: The Thermodynamic Solar System joins two incomplete technologies, the heat pump and the solar thermal collector. Heat pumps are quite efficient equipment but the heat they produce from their renewable component varies only according to changes in the temperature of the environment. Thermal solar collectors are the best source of heat on hot and sunny days, but they are totally inefficient whenever there is no sun. The thermodynamic Solar Technology manages to surpass the limitations of both the heat pump and solar collector. Through the cooling liquid (R134a or R407c ) which covers a closed circuit, the liquid goes into the solar panel and extract the thermal energy of sun , rain, wind, environment temperature and other climate factors . During this process the liquid gains heat in a more favorable way than a heat pump. after this stage , the heat it transferred to an exchanger with the help of a small compressor, which heats the water , The liquid cools down and the circuit is repeated. As the fluid has a boiling temperature of approximately -30C , the system works even when there is no sun and it even works at night, hail, rain, wind or shine , unlike the traditional solar thermal system. The energy consumption of the system is basically the same as fridge compressor that makes the liquid circulate. there are no ventilators that help the evaporation process, of defrost cycles, which imply unnecessary energy consumption, unlike what happened with heat pump
A82: The Thermodynamic Solar technology offers high performance even at night, with rain, or on overcast days, this being an advantage over conventional solar panels whose performance is limited as they rely exclusively on direct solar radiation and a compulsory southward orientation (Northern Hemisphere).
A91: NEXT-GEN THERMODYNAMICS SOLAR PANEL COLLECTOR Latest generation thermodynamic solar collector: it is a roll-bond panel with double channel through which the fluid refrigerant circulates, being able of providing high performance at night and in adverse climate conditions. Life span of more than 10 years: the panel is made of anodized aluminum 30 micron, which ensures The following properties • Great toughness at high and low temperatures. • High surface hardness. • Resistance to abrasion and weakening. • High protection against dust and dampness. • Corrosion-resistant. User-friendly transport and easy handling systems: small size 2 m x 0,8 m. Versatility: easy integration on facades, roofs or any other surface. It is not necessary to reinforce structures as it is a lightweight panel, 8 kg. Optimized solar catchment area: both sides of the panel, 3,20 sqm. No need to be south orientated (Northern Hemisphere). Vindsol recommends to orientate the collector as much as possible to the sun and exposed to the elements, such as wind and rain. Regular maintenance is not necessary.
A107: NEXT-GEN THERMODYNAMICS SOLAR HEAT PUMP
A109: TECHNICAL SPECIFICATION
A110: Model | C110: MiNi2-300
A112: Thermodynamic Solar Panel
A113: Material & Finish | C113: Powder coated Anodised aluminium Alloy panel
A114: Thickness | B114: L X W X T (mm) | C114: 2 mm aluminium for increased mechanical strength
A115: Protection | C115: Corrosion resistant and adaptability to all weathers
A116: Dimensions L X W X T | B116: mm | C116: 2000 X 800 * 20
A117: Maximum working Pr. | B117: Bar | C117: 10
A118: Test pressure | B118: Bar | C118: 15
A119: Maximum exposure temp. | B119: °C | C119: 100
A120: Minimum running temp. | B120: °C | C120: 10
A121: Qty | B121: Nos | C121: =VLOOKUP(C110,Sheet2!A47:AF52,10) -> 2
A122: Thermodynamic Box
A123: Absorbed power KW (Average/Max) | C123: 0.72 KW
A124: Thermal Calorific power (Average/Max) | C124: 3.6 KW
A125: Compressor Type | C125: Rotary Type - Heat pump COmpressor
A126: Throttle Type | C126: Electronic expansion valve (EEV)
A127: Rated outlet water temp.℃ | C127: 50-55 Deg
A128: Max outlet water temp.℃ | C128: 55 Deg
A129: Power V/Ph/Hz | C129: 220V/1PH/ 50Hz
A130: Heat exchanger type | C130: High efficiency tube in tube heat exchanger
A131: Heat exchanger No. | C131: 1
A132: Controller type | C132: Intelligent PCB & LCD
A133: Ambient Temperature | C133: (0℃~+45 ℃)
A134: Low pressure protection | C134: Yes
A135: High pressure protection | C135: Yes
A136: Automatic defroting system | C136: Yes
A137: Overload protection | C137: Yes
A138: Noise in 1 meter | C138: 50 dB
A139: Water pipe size | C139: 25 NB
A140: Water flow volume | C140: 2 M3/hr
A141: Circulation Pump | C141: Additional
A142: Net Weight | B142: Kg | C142: 50 Kg Apprx
A143: Cabinet | B143: Type | C143: =VLOOKUP(C110,Sheet2!A47:AF52,18) -> Stainless Steel / Galvanised Steek
A144: Dimension | B144: LxWXH | C144: 700 X 700 X 1000
A145: Electrical support power | C145: 2 Kw
A146: Circulation Pump | C146: =VLOOKUP(C110,Sheet2!A47:AF52,16) -> Builtin Hot water circualtor Pump
A147: Cabinet | B147: Type | C147: =VLOOKUP(C110,Sheet2!A47:AF52,18) -> Stainless Steel / Galvanised Steek
A148: Dimension | B148: LxWXH | C148: =VLOOKUP(C110,Sheet2!A47:AF52,19) -> 500 X 450 X 375
A149: Refrigerant
A150: Cooling Fluid * | C150: =VLOOKUP(C110,Sheet2!A47:AF52,20) -> R134a
A151: Piping Material | C151: =VLOOKUP(C110,Sheet2!A47:AF52,21) -> Copper (DHP ISO1337)
A152: Line of liquid | C152: =VLOOKUP(C110,Sheet2!A47:AF52,22) -> 3/8"
A153: Line of aspiration | C153: =VLOOKUP(C110,Sheet2!A47:AF52,23) -> 1/2"
A154: Storage Water Heater
A155: Volume | B155: Litres | C155: 200 Lts Imported Glass Lined
A156: Type of internal Tank | C156: Cellipsoidal RC premium Steel
A157: Outer Shell material | C157: Pre Coated GI 0.5 mm
A158: Inner Tank Dia | C158: 480 mm
A159: Outer tank dia | C159: 580 mm
A160: Coating of internal Tank | C160: QuartzBlue Glass lining
A161: Tank Insualtion | C161: High density compressed PUF insualtion 50 mm
A162: Water Inlet / Outlet | B162: In | C162: 3/4"
A163: Circulation water inlet/outlet | B163: In | C163: 3/4"
A164: Working pressure | B164: Bar | C164: 7
A165: Test pressure | B165: Bar | C165: 10
A166: Maximum water temp. | B166: °C | C166: 75
A167: Water temperature | B167: °C | C167: =VLOOKUP(C110,Sheet2!A47:AF52,30) -> 55
A168: ELECTRIC BOARD - ONE TOUCH PCB CONTROLLER
A169: One touch intelligent controller with Touch screen design, clear working condition displaying, and self-check function of error.
A170: Power feed | C170: 220V/1PH/ 50Hz
A171: Controller | C171: =VLOOKUP(C110,Sheet2!A47:AF52,32) -> Next Gen PCB controller
A172: Testing condition : * Heating: Ambient temp. (DB/WB): 20℃/15℃, water temp. (input/output): 15℃/55℃. The above data is only for reference: specific data is subject to the product
A173: COPPER TUBING aand plumbing UNITS AND ACCESSORIES - To be arranged locally
G174: Consumable like copper piping along with insualtion and required accessories is included 2. Complete Plumbing with neceesary valve along with insulation will be in scope of customer
L177: -
A181: Commercial Offer
A182: Vindsol Make Next Gen Commercial Thermodynamics solar heat pump for 200 lts hot water cpacity , complete with heat pump + 2 nos Thermodynamics Panel + 200 Lts Storage Tank + fixing clamp Accessories | F182: Unit | G182: Qty | H182: Rate | I182: Amount
F183: Set | G183: 1 | H183: 172000 | I183: =H183*G183 -> 172000
A188: Safety Kit Pack for Pressurised Tank - Additional Required
A189: Vacuum Relief Valve GST @ 18% extra | C189: WATTS imported 3/4 inch lead free Vacuum Relief Valve automatically allows air to enter into the piping system to prevent vacuum conditions that could siphon water from the system and damage water equipment. | G189: included | H189: 1
A190: Safety Pressure Relief Valve GST @ 18% extra | C190: Safety Pressure Relief Valve 1/2″ 3 Bar , Protects hot water cylinders and heating components from high pressure
A191: Automatic Air Vent valve GST @ 18% extra | C191: Brass Automatic Air Vent valve 1/2'' BSP male thread. It automatically removes trapped air from a central heating installation.
A192: Water Circualtion pumps GST @ 12% extra | C192: Mechlion Make Stainless steel Horizontal multistage pump Model : MHM 4-20 , 0.75 HP | G192: included | H192: 1
G193: Total
A194: INR : One Lakh forty Seventy two thousand only
A195: TERMS & CONDITIONS
A196: Prices applicable are at Site in Vidyaranya pura , Bangalore
A197: Packing and forwarding cost : Included
A198: Payment to be made 50% as advance along with order against proforma and balance priior to delivery
A199: Delivery : within 2-3 weeks
A200: Panel Installtion Structure will be in customer scope
A201: Online Installation and commissioning Support will be provided
A202: Note: The Complete System Includes the 1. thermodynamic box 2. Thermodynamic panels with clamps 3. Hot water Storage Tank of respective volume. Consumable like copper piping will required accessories and fittigs along with insulation will be in customers scope Complete Plumbing with insulation will be in scope of customer
A203: Complete water Heating Solutions | B203: Mechzephyr Engineering Pvt Ltd Shed No A 70 , KSSIDC , Bommasandra Industrial Area, Bangalore – 560099 Mobile : 9900095490 | Email: deepak@vindsol.in | G203: Domestic water heat pumps Commercial Water Heat Pumps Next Gen Thermodynamics Heat Pumps Swimming pool heat pump

Sheet Mini 2 300
A1: Technical Data Sheet - Domestic Thermodynamics Solar Heat Pump
A53: NEXT-GEN THERMODYNAMICS SOLAR HEAT PUMP
A55: Technical Data Sheet - Domestic Thermodynamics Solar Heat Pump
A59: NEXT-GEN THERMODYNAMICS SOLAR HEAT PUMP | E59: The Thermodynamic Solar System joins two incomplete technologies, the heat pump and the solar thermal collector. Heat pumps are quite efficient equipment but the heat they produce from their renewable component varies only according to changes in the temperature of the environment. Thermal solar collectors are the best source of heat on hot and sunny days, but they are totally inefficient whenever there is no sun. The thermodynamic Solar Technology manages to surpass the limitations of both the heat pump and solar collector. Through the cooling liquid (R134a or R407c ) which covers a closed circuit, the liquid goes into the solar panel and extract the thermal energy of sun , rain, wind, environment temperature and other climate factors . During this process the liquid gains heat in a more favorable way than a heat pump. after this stage , the heat it transferred to an exchanger with the help of a small compressor, which heats the water , The liquid cools down and the circuit is repeated. As the fluid has a boiling temperature of approximately -30C , the system works even when there is no sun and it even works at night, hail, rain, wind or shine , unlike the traditional solar thermal system. The energy consumption of the system is basically the same as fridge compressor that makes the liquid circulate. there are no ventilators that help the evaporation process, of defrost cycles, which imply unnecessary energy consumption, unlike what happened with heat pump
A82: The Thermodynamic Solar technology offers high performance even at night, with rain, or on overcast days, this being an advantage over conventional solar panels whose performance is limited as they rely exclusively on direct solar radiation and a compulsory southward orientation (Northern Hemisphere).
A91: NEXT-GEN THERMODYNAMICS SOLAR PANEL COLLECTOR Latest generation thermodynamic solar collector: it is a roll-bond panel with double channel through which the fluid refrigerant circulates, being able of providing high performance at night and in adverse climate conditions. Life span of more than 10 years: the panel is made of anodized aluminum 30 micron, which ensures The following properties • Great toughness at high and low temperatures. • High surface hardness. • Resistance to abrasion and weakening. • High protection against dust and dampness. • Corrosion-resistant. User-friendly transport and easy handling systems: small size 2 m x 0,8 m. Versatility: easy integration on facades, roofs or any other surface. It is not necessary to reinforce structures as it is a lightweight panel, 8 kg. Optimized solar catchment area: both sides of the panel, 3,20 sqm. No need to be south orientated (Northern Hemisphere). Vindsol recommends to orientate the collector as much as possible to the sun and exposed to the elements, such as wind and rain. Regular maintenance is not necessary.
A107: NEXT-GEN THERMODYNAMICS SOLAR HEAT PUMP
A109: TECHNICAL SPECIFICATION
A110: Model | C110: MiNi2-300
A112: Thermodynamic Solar Panel
A113: Material & Finish | C113: Powder coated Anodised aluminium Alloy panel
A114: Thickness | B114: L X W X T (mm) | C114: 2 mm aluminium for increased mechanical strength
A115: Protection | C115: Corrosion resistant and adaptability to all weathers
A116: Dimensions L X W X T | B116: mm | C116: 2000 X 800 * 20
A117: Maximum working Pr. | B117: Bar | C117: 10
A118: Test pressure | B118: Bar | C118: 15
A119: Maximum exposure temp. | B119: °C | C119: 100
A120: Minimum running temp. | B120: °C | C120: 10
A121: Qty | B121: Nos | C121: =VLOOKUP(C110,Sheet2!A47:AF52,10) -> 2
A122: Thermodynamic Box
A123: Absorbed power KW (Average/Max) | C123: 0.72 KW
A124: Thermal Calorific power (Average/Max) | C124: 3.6 KW
A125: Compressor Type | C125: Rotary Type - Heat pump COmpressor
A126: Throttle Type | C126: Electronic expansion valve (EEV)
A127: Rated outlet water temp.℃ | C127: 50-55 Deg
A128: Max outlet water temp.℃ | C128: 55 Deg
A129: Power V/Ph/Hz | C129: 220V/1PH/ 50Hz
A130: Heat exchanger type | C130: High efficiency tube in tube heat exchanger
A131: Heat exchanger No. | C131: 1
A132: Controller type | C132: Intelligent PCB & LCD
A133: Ambient Temperature | C133: (0℃~+45 ℃)
A134: Low pressure protection | C134: Yes
A135: High pressure protection | C135: Yes
A136: Automatic defroting system | C136: Yes
A137: Overload protection | C137: Yes
A138: Noise in 1 meter | C138: 50 dB
A139: Water pipe size | C139: 25 NB
A140: Water flow volume | C140: 2 M3/hr
A141: Circulation Pump | C141: Additional
A142: Net Weight | B142: Kg | C142: 50 Kg Apprx
A143: Cabinet | B143: Type | C143: =VLOOKUP(C110,Sheet2!A47:AF52,18) -> Stainless Steel / Galvanised Steek
A144: Dimension | B144: LxWXH | C144: 700 X 700 X 1000
A145: Electrical support power | C145: 2 Kw
A146: Circulation Pump | C146: =VLOOKUP(C110,Sheet2!A47:AF52,16) -> Builtin Hot water circualtor Pump
A147: Cabinet | B147: Type | C147: =VLOOKUP(C110,Sheet2!A47:AF52,18) -> Stainless Steel / Galvanised Steek
A148: Dimension | B148: LxWXH | C148: =VLOOKUP(C110,Sheet2!A47:AF52,19) -> 500 X 450 X 375
A149: Refrigerant
A150: Cooling Fluid * | C150: =VLOOKUP(C110,Sheet2!A47:AF52,20) -> R134a
A151: Piping Material | C151: =VLOOKUP(C110,Sheet2!A47:AF52,21) -> Copper (DHP ISO1337)
A152: Line of liquid | C152: =VLOOKUP(C110,Sheet2!A47:AF52,22) -> 3/8"
A153: Line of aspiration | C153: =VLOOKUP(C110,Sheet2!A47:AF52,23) -> 1/2"
A154: Storage Water Heater
A155: Volume | B155: Litres | C155: 300 Lts Imported Glass Lined
A156: Type of internal Tank | C156: Cellipsoidal RC premium Steel
A157: Outer Shell material | C157: Pre Coated GI 0.5 mm
A158: Inner Tank Dia | C158: 480 mm
A159: Outer tank dia | C159: 580 mm
A160: Coating of internal Tank | C160: QuartzBlue Glass lining
A161: Tank Insualtion | C161: High density compressed PUF insualtion 50 mm
A162: Water Inlet / Outlet | B162: In | C162: 3/4"
A163: Circulation water inlet/outlet | B163: In | C163: 3/4"
A164: Working pressure | B164: Bar | C164: 7
A165: Test pressure | B165: Bar | C165: 10
A166: Maximum water temp. | B166: °C | C166: 75
A167: Water temperature | B167: °C | C167: =VLOOKUP(C110,Sheet2!A47:AF52,30) -> 55
A168: ELECTRIC BOARD - ONE TOUCH PCB CONTROLLER
A169: One touch intelligent controller with Touch screen design, clear working condition displaying, and self-check function of error.
A170: Power feed | C170: 220V/1PH/ 50Hz
A171: Controller | C171: =VLOOKUP(C110,Sheet2!A47:AF52,32) -> Next Gen PCB controller
A172: Testing condition : * Heating: Ambient temp. (DB/WB): 20℃/15℃, water temp. (input/output): 15℃/55℃. The above data is only for reference: specific data is subject to the product
A173: COPPER TUBING aand plumbing UNITS AND ACCESSORIES - To be arranged locally
G174: Consumable like copper piping will required accessories and fittigs along with insulation will be in customers scope as per site condition. Complete Plumbing with insulation will be in scope of customer
L177: -
A181: Commercial Offer
A182: Vindsol Make Next Gen Commercial Thermodynamics solar heat pump for 200 lts hot water cpacity , complete with heat pump + 2 nos Thermodynamics Panel + 200 Lts Storage Tank + fixing clamp Accessories | F182: Unit | G182: Qty | H182: Rate | I182: Amount
F183: Set | G183: 1
A188: Safety Kit Pack for Pressurised Tank - Additional Required
A189: Vacuum Relief Valve GST @ 18% extra | C189: WATTS imported 3/4 inch lead free Vacuum Relief Valve automatically allows air to enter into the piping system to prevent vacuum conditions that could siphon water from the system and damage water equipment. | G189: included | H189: 1
A190: Safety Pressure Relief Valve GST @ 18% extra | C190: Safety Pressure Relief Valve 1/2″ 3 Bar , Protects hot water cylinders and heating components from high pressure
A191: Automatic Air Vent valve GST @ 18% extra | C191: Brass Automatic Air Vent valve 1/2'' BSP male thread. It automatically removes trapped air from a central heating installation.
A192: Water Circualtion pumps GST @ 12% extra | C192: Mechlion Make Hot water circualor pump for return pump Model : HWS25-7 , 100 watts | G192: included | H192: 1
A193: Water Circualtion pumps GST @ 12% extra | C193: Mechlion Make Hot water circualor pump for return pump Model : HWS25-7 , 100 watts | G193: No | H193: 1 | I193: 9000
A194: Water Circualtion pumps GST @ 12% extra | C194: Mechlion Make Automatic ocntrol panel with digital timer for the return pump | G194: No | H194: 1 | I194: 7900
A195: Mechlion make Single Pump Vfd booster with Inetegrated VFD ( Variable prequency drive) | C195: Mechlion make Single Pump Vfd booster with Inetegrated VFD ( Variable prequency drive) with 100 % Stainless steel Horizontal multistage Pump with IE3 class motor , 3 phase and 8 litres of pressure tank along with SS 5 way valve Model No : 4-50 , 0.75 KW | G195: No | H195: 1 | I195: 62000
G196: Total
A197: INR : Two Lakh ninety eight thousand nine hundred only
A198: TERMS & CONDITIONS
A199: Prices applicable are Ex.Works , Bangalore
A200: Packing and forwarding cost 2 % extra
A201: Payment to be made 50% as advance along with order against proforma and balance priior to delivery
A202: Delivery : within 3-4 weeks
A203: Panel Installtion Structure will be in customer scope
A204: Online Installation and commissioning Support will be provided
A205: Note: The Complete System Includes the 1. thermodynamic box 2. Thermodynamic panels with clamps 3. Hot water Storage Tank of respective volume. Consumable like copper piping will required accessories and fittigs along with insulation will be in customers scope Complete Plumbing with insulation will be in scope of customer
A206: Complete water Heating Solutions | B206: Mechzephyr Engineering Pvt Ltd Shed No A 70 , KSSIDC , Bommasandra Industrial Area, Bangalore – 560099 Mobile : 9900095490 | Email: deepak@vindsol.in | G206: Domestic water heat pumps Commercial Water Heat Pumps Next Gen Thermodynamics Heat Pumps Swimming pool heat pump

Sheet Mini 4 500
A1: Technical Data Sheet - Domestic Thermodynamics Solar Heat Pump
A53: NEXT-GEN THERMODYNAMICS SOLAR HEAT PUMP
A55: Technical Data Sheet - Domestic Thermodynamics Solar Heat Pump
A59: NEXT-GEN THERMODYNAMICS SOLAR HEAT PUMP | E59: The Thermodynamic Solar System joins two incomplete technologies, the heat pump and the solar thermal collector. Heat pumps are quite efficient equipment but the heat they produce from their renewable component varies only according to changes in the temperature of the environment. Thermal solar collectors are the best source of heat on hot and sunny days, but they are totally inefficient whenever there is no sun. The thermodynamic Solar Technology manages to surpass the limitations of both the heat pump and solar collector. Through the cooling liquid (R134a or R407c ) which covers a closed circuit, the liquid goes into the solar panel and extract the thermal energy of sun , rain, wind, environment temperature and other climate factors . During this process the liquid gains heat in a more favorable way than a heat pump. after this stage , the heat it transferred to an exchanger with the help of a small compressor, which heats the water , The liquid cools down and the circuit is repeated. As the fluid has a boiling temperature of approximately -30C , the system works even when there is no sun and it even works at night, hail, rain, wind or shine , unlike the traditional solar thermal system. The energy consumption of the system is basically the same as fridge compressor that makes the liquid circulate. there are no ventilators that help the evaporation process, of defrost cycles, which imply unnecessary energy consumption, unlike what happened with heat pump
A82: The Thermodynamic Solar technology offers high performance even at night, with rain, or on overcast days, this being an advantage over conventional solar panels whose performance is limited as they rely exclusively on direct solar radiation and a compulsory southward orientation (Northern Hemisphere).
A91: NEXT-GEN THERMODYNAMICS SOLAR PANEL COLLECTOR Latest generation thermodynamic solar collector: it is a roll-bond panel with double channel through which the fluid refrigerant circulates, being able of providing high performance at night and in adverse climate conditions. Life span of more than 10 years: the panel is made of anodized aluminum 30 micron, which ensures The following properties • Great toughness at high and low temperatures. • High surface hardness. • Resistance to abrasion and weakening. • High protection against dust and dampness. • Corrosion-resistant. User-friendly transport and easy handling systems: small size 2 m x 0,8 m. Versatility: easy integration on facades, roofs or any other surface. It is not necessary to reinforce structures as it is a lightweight panel, 8 kg. Optimized solar catchment area: both sides of the panel, 3,20 sqm. No need to be south orientated (Northern Hemisphere). Vindsol recommends to orientate the collector as much as possible to the sun and exposed to the elements, such as wind and rain. Regular maintenance is not necessary.
A107: NEXT-GEN THERMODYNAMICS SOLAR HEAT PUMP
A109: TECHNICAL SPECIFICATION
A110: Model | C110: MiNi4-500
A112: Thermodynamic Solar Panel
A113: Material & Finish | C113: Powder coated Anodised aluminium Alloy panel
A114: Thickness | B114: L X W X T (mm) | C114: 2 mm aluminium for increased mechanical strength
A115: Protection | C115: Corrosion resistant and adaptability to all weathers
A116: Dimensions L X W X T | B116: mm | C116: 2000 X 800 * 20
A117: Maximum working Pr. | B117: Bar | C117: 10
A118: Test pressure | B118: Bar | C118: 15
A119: Maximum exposure temp. | B119: °C | C119: 100
A120: Minimum running temp. | B120: °C | C120: 10
A121: Qty | B121: Nos | C121: 8
A122: Thermodynamic Box
A123: Absorbed power KW (Average/Max) | C123: 0.9/1.78 KW
A124: Thermal Calorific power (Average/Max) | C124: 3.55/7.16 KW
A125: Compressor Type | C125: Rotary Type - Heat pump COmpressor
A126: Throttle Type | C126: Electronic expansion valve (EEV)
A127: Rated outlet water temp.℃ | C127: 50-55 Deg
A128: Max outlet water temp.℃ | C128: 55 Deg
A129: Power V/Ph/Hz | C129: 220V/1PH/ 50Hz
A130: Heat exchanger type | C130: High efficiency tube in tube heat exchanger
A131: Heat exchanger No. | C131: 1
A132: Controller type | C132: Intelligent PCB & LCD
A133: Ambient Temperature | C133: (0℃~+45 ℃)
A134: Low pressure protection | C134: Yes
A135: High pressure protection | C135: Yes
A136: Automatic defroting system | C136: Yes
A137: Overload protection | C137: Yes
A138: Noise in 1 meter | C138: 50 dB
A139: Water pipe size | C139: 25 NB
A140: Water flow volume | C140: 2 M3/hr
A141: Circulation Pump | C141: Additional
A142: Net Weight | B142: Kg | C142: 50 Kg Apprx
A143: Cabinet | B143: Type | C143: =VLOOKUP(C110,Sheet2!A47:AF52,18) -> Stainless Steel / Galvanised Steek
A144: Dimension | B144: LxWXH | C144: 700 X 700 X 1000
A145: Electrical support power | C145: 2 Kw
A146: Circulation Pump | C146: =VLOOKUP(C110,Sheet2!A47:AF52,16) -> Builtin Hot water circualtor Pump
A147: Cabinet | B147: Type | C147: =VLOOKUP(C110,Sheet2!A47:AF52,18) -> Stainless Steel / Galvanised Steek
A148: Dimension | B148: LxWXH | C148: =VLOOKUP(C110,Sheet2!A47:AF52,19) -> 500 X 450 X 375
A149: Refrigerant
A150: Cooling Fluid * | C150: =VLOOKUP(C110,Sheet2!A47:AF52,20) -> R134a
A151: Piping Material | C151: =VLOOKUP(C110,Sheet2!A47:AF52,21) -> Copper (DHP ISO1337)
A152: Line of liquid | C152: =VLOOKUP(C110,Sheet2!A47:AF52,22) -> 3/8"
A153: Line of aspiration | C153: =VLOOKUP(C110,Sheet2!A47:AF52,23) -> 1/2"
A154: Storage Water Heater
A155: Volume | B155: Litres | C155: 500 Lts Glass Lined
A156: Type of internal Tank | C156: Cellipsoidal RC premium Steel
A157: Outer Shell material | C157: Pre Coated GI 0.5 mm
A158: Inner Tank Dia | C158: 610 mm
A159: Outer tank dia | C159: 710 mm
A160: Coating of internal Tank | C160: QuartzBlue Glass lining
A161: Tank Insualtion | C161: High density compressed PUF insualtion 50 mm
A162: Water Inlet / Outlet | B162: In | C162: 3/4"
A163: Circulation water inlet/outlet | B163: In | C163: 3/4"
A164: Working pressure | B164: Bar | C164: 5
A165: Test pressure | B165: Bar | C165: 8
A166: Maximum water temp. | B166: °C | C166: 65
A167: Water temperature | B167: °C | C167: =VLOOKUP(C110,Sheet2!A47:AF52,30) -> 55
A168: ELECTRIC BOARD - ONE TOUCH PCB CONTROLLER
A169: One touch intelligent controller with Touch screen design, clear working condition displaying, and self-check function of error.
A170: Power feed | C170: 220V/1PH/ 50Hz
A171: Controller | C171: =VLOOKUP(C110,Sheet2!A47:AF52,32) -> Next Gen PCB controller
A172: Testing condition : * Heating: Ambient temp. (DB/WB): 20℃/15℃, water temp. (input/output): 15℃/55℃. The above data is only for reference: specific data is subject to the product
A173: COPPER TUBING aand plumbing UNITS AND ACCESSORIES
E174: “Consumables such as copper piping, including necessary accessories, fittings, and insulation, are considered for a standard length of 5 meters. Any additional requirement beyond this will be under the customer’s scope, depending on site conditions. The complete plumbing work, including insulation for the distribution line, shall also fall within the customer’s scope.”

Sheet Sheet1
A7: S.No | B7: Decsription | C7: Unit | D7: Qty
A8: 1 | B8: Thermodybamic Solar panel 2 NO s | C8: No | D8: 1
B9: In plywood o rwooden case
B10: 2200 X 100 X 1200 mm Box APPRX, 50 Kg
A17: 2 | B17: Thermodynamic BOX with accessories Packed in wooden case , Apppx Dimesnion : 800 X 500 X 600 , Appx 75 Kg | C17: No | D17: 1
A27: 3 | B27: GLASS Lined Hot water Storage Tank , 300 Lts , 0.82 CBM , Apprx 100 Kg with xtra wooden Packing | C27: No | D27: 1

Sheet QTN
A1: Techno - Commercial Data Sheet - Domestic Thermodynamics Solar Heat Pump
A53: NEXT-GEN THERMODYNAMICS SOLAR HEAT PUMP
A55: Technical Data Sheet - Domestic Thermodynamics Solar Heat Pump
A59: NEXT-GEN THERMODYNAMICS SOLAR HEAT PUMP | E59: The Thermodynamic Solar System joins two incomplete technologies, the heat pump and the solar thermal collector. Heat pumps are quite efficient equipment but the heat they produce from their renewable component varies only according to changes in the temperature of the environment. Thermal solar collectors are the best source of heat on hot and sunny days, but they are totally inefficient whenever there is no sun. The thermodynamic Solar Technology manages to surpass the limitations of both the heat pump and solar collector. Through the cooling liquid (R134a or R407c ) which covers a closed circuit, the liquid goes into the solar panel and extract the thermal energy of sun , rain, wind, environment temperature and other climate factors . During this process the liquid gains heat in a more favorable way than a heat pump. after this stage , the heat it transferred to an exchanger with the help of a small compressor, which heats the water , The liquid cools down and the circuit is repeated. As the fluid has a boiling temperature of approximately -30C , the system works even when there is no sun and it even works at night, hail, rain, wind or shine , unlike the traditional solar thermal system. The energy consumption of the system is basically the same as fridge compressor that makes the liquid circulate. there are no ventilators that help the evaporation process, of defrost cycles, which imply unnecessary energy consumption, unlike what happened with heat pump
A82: The Thermodynamic Solar technology offers high performance even at night, with rain, or on overcast days, this being an advantage over conventional solar panels whose performance is limited as they rely exclusively on direct solar radiation and a compulsory southward orientation (Northern Hemisphere).
A90: NEXT-GEN THERMODYNAMICS SOLAR PANEL COLLECTOR Latest generation thermodynamic solar collector: it is a roll-bond panel with double channel through which the fluid refrigerant circulates, being able of providing high performance at night and in adverse climate conditions. Life span of more than 10 years: the panel is made of anodized aluminum 30 micron, which ensures The following properties • Great toughness at high and low temperatures. • High surface hardness. • Resistance to abrasion and weakening. • High protection against dust and dampness. • Corrosion-resistant. User-friendly transport and easy handling systems: small size 2 m x 0,8 m. Versatility: easy integration on facades, roofs or any other surface. It is not necessary to reinforce structures as it is a lightweight panel, 8 kg. Optimized solar catchment area: both sides of the panel, 3,20 sqm. No need to be south orientated (Northern Hemisphere). Vindsol recommends to orientate the collector as much as possible to the sun and exposed to the elements, such as wind and rain. Regular maintenance is not necessary.
A107: NEXT-GEN THERMODYNAMICS SOLAR HEAT PUMP
A109: TECHNICAL SPECIFICATION
A110: Model | C110: VTDHP 24MAX3000
A112: Thermodynamic Solar Panel
A113: Material & Finish | C113: Powder coated Anodised aluminium Alloy panel
A114: Thickness | B114: L X W X T (mm) | C114: 2 mm aluminium for increased mechanical strength
A115: Protection | C115: Corrosion resistant and adaptability to all weathers
A116: Dimensions L X W X T | B116: mm | C116: 2000 X 800 * 20
A117: Maximum working Pr. | B117: Bar | C117: 10
A118: Test pressure | B118: Bar | C118: 15
A119: Maximum exposure temp. | B119: °C | C119: 100
A120: Minimum running temp. | B120: °C | C120: 10
A121: Qty | B121: Nos | C121: 24
A122: Exposed collecting surface | B122: m2 | C122: 38.4
A123: Thermodynamic Box
A124: Absorbed power KW (Average/Max) | C124: 4.2/6.25 KW
A125: Thermal Calorific power (Average/Max) | C125: 16 / 28 KW
A126: Compressor Type | C126: Scroll - Copeland Emerson
A127: Throttle Type | C127: Electronic expansion valve (EEV)
A128: Rated outlet water temp.℃ | C128: 55 Deg
A129: Max outlet water temp.℃ | C129: 55 Deg
A130: Power V/Ph/Hz | C130: 380 ～415V/3PH/ 50Hz
A131: Heat exchanger type | C131: High efficiency tube in tube heat exchanger
A132: Heat exchanger No. | C132: 1
A133: Controller type | C133: Intelligent PCB & LCD
A134: Ambient Temperature | C134: (0℃~+45 ℃)
A135: Low pressure protection | C135: Yes
A136: High pressure protection | C136: Yes
A137: Automatic defroting system | C137: Yes
A138: Overload protection | C138: Yes
A139: Noise in 1 meter | C139: 50 dB
A140: Water pipe size | C140: 25 NB
A141: Water flow volume | C141: 4 M3/hr
A142: Circulation Pump | C142: Additional
A143: Net Weight | B143: Kg | C143: 200 Kg Apprx
A144: Cabinet | B144: Type | C144: =VLOOKUP(C110,Sheet2!A47:AF52,18) -> Stainless Steel / Galvanised Steek
A145: Dimension | B145: LxWXH | C145: 700 X 700 X 1000
A146: Refrigerant
A147: Cooling Fluid * | C147: R407c
A148: Piping Material | C148: =VLOOKUP(C110,Sheet2!A47:AF52,21) -> Copper (DHP ISO1337)
A149: Line of liquid | C149: 3/4"
A150: Line of aspiration | C150: 1-1/8"
A151: Storage Water Heater
A152: Water tank volume lts | B152: Litres | C152: 3000
A153: Insulation material | C153: Insulation Materials Rockwool thickness 100 mm
A154: Cladding material | C154: 24 gauge Aluminum cladding.
A155: Shell / Dish end thickness | C155: 5 / 5 mm
A156: Inner tank coating | C156: Enamelled Anti corrosion Epoxy coat
A157: Inner tank material | C157: MS
A158: Design working pressure | C158: 6
A159: Testing pressure | C159: 4
A160: Electrical backup Capac | B160: Nos | C160: 4 KW X 3 Nos
A161: Qty - Nos | B161: Nos | C161: 1
A162: ELECTRIC BOARD - ONE TOUCH PCB CONTROLLER
A163: One touch intelligent controller with Touch screen design, clear working condition displaying, and self-check function of error.
A164: Power feed | C164: 380 ～415V/3PH/ 50Hz
A165: Controller | C165: =VLOOKUP(C110,Sheet2!A47:AF52,32) -> Next Gen PCB controller
A166: Testing condition : * Heating: Ambient temp. (DB/WB): 20℃/15℃, water temp. (input/output): 15℃/55℃. The above data is only for reference: specific data is subject to the product
A167: PANEL FITTING UNITS AND ACCESSORIES
A175: Commercial Offer
A176: Vindsol Make Next Gen Commercial Thermodynamics solar heat pump for 3000 lts hot water cpacity , complete with heat pump + 24 nos Thermodynamics Panel + 3000 Lt sStorage Tank + fixing clamp Accessories | F176: Unit | G176: Qty | H176: Rate | I176: Amount
F177: Set | G177: 1 | H177: 1675000 | I177: =H177*G177 -> 1675000
A182: Safety Kit Pack for Pressurised Tank | G182: Rate | H182: Qty | I182: Amount
A183: Vacuum Relief Valve GST @ 18% extra | C183: WATTS imported 3/4 inch lead free Vacuum Relief Valve automatically allows air to enter into the piping system to prevent vacuum conditions that could siphon water from the system and damage water equipment. | G183: Included | H183: 1
A184: Safety Pressure Relief Valve GST @ 18% extra | C184: Safety Pressure Relief Valve 1/2″ 3 Bar , Protects hot water cylinders and heating components from high pressure
A185: Automatic Air Vent valve GST @ 18% extra | C185: Brass Automatic Air Vent valve 1/2'' BSP male thread. It automatically removes trapped air from a central heating installation.
A186: Water Circualtion pumps GST @ 12% extra | C186: Mechlion Make Stainless steel Horizontal multistage pump Model : MHM 4-20 , 0.75 HP | G186: Included | H186: 1
A187: Fuly automatic control panel GST @ 18% extra | C187: Fuly automatic control panel with timer function | H187: 1
A188: Electric Backup GST @ 18% extra | C188: Electric Back up Heater with Heating element of 4 KW heating capacity , with Solid state relay and built in Themrostat | H188: 3
G189: Total | I189: =I177 -> 1675000
G190: GST @ 18 % | I190: =I189*0.18 -> 301500
A191: TERMS & CONDITIONS | G191: Grand Total | I191: =I190+I189 -> 1976500
A192: Prices applicable are Ex.Godown .F.O.R, Transportation charges extra at actual will be to dealer’s account.
A193: Packing and forwarding cost 2 % extra
A194: GST @ 18 % Extra as indicated
A195: Receiving of material and handling of material at site will be in customer scope
A196: Payment to be made 50% as advance along with order against proforma.
A197: Delivery : within 6-8 weeks
A198: Panel Installtion Structure will be in customer scope
A199: During the Installation and commissioning customer will provide accomodation and food for 2-3 technician of ours
A200: Note: The Complete System Includes the 1. thermodynamic box 2. Thermodynamic panels with clamps and 3. Hot water Storage Tank of respective volume. Consumable like copper piping will required accessories and fittigs along with insulation will be in customers scope Complete Plumbing with insulation will be in scope of customer
A202: Complete water Heating Solutions | B202: Mechzephyr Engineering Pvt Ltd Shed No A 70 , KSSIDC , Bommasandra Industrial Area, Bangalore – 560099 Mobile : 9900095490 | Email: deepak@vindsol.in | G202: Domestic water heat pumps Commercial Water Heat Pumps Next Gen Thermodynamics Heat Pumps Swimming pool heat pump

Sheet Sheet2
A1: Model | B1: MiNi1-200 | C1: MiNi1-300 | D1: MiNi2-300 | E1: MiNi2-500 | F1: MiNi4-500
A2: Material & Finish | B2: Powder coated Anodised aluminium Alloy panel | C2: Powder coated Anodised aluminium Alloy panel | D2: Powder coated Anodised aluminium Alloy panel | E2: Powder coated Anodised aluminium Alloy panel | F2: Powder coated Anodised aluminium Alloy panel
A3: Thickness | B3: 2mm aluminium for increased mechanical strength | C3: 2mm aluminium for increased mechanical strength | D3: 2mm aluminium for increased mechanical strength | E3: 2mm aluminium for increased mechanical strength | F3: 2mm aluminium for increased mechanical strength
A4: Protection | B4: Corrosion resistant and adaptability to all weathers | C4: Corrosion resistant and adaptability to all weathers | D4: Corrosion resistant and adaptability to all weathers | E4: Corrosion resistant and adaptability to all weathers | F4: Corrosion resistant and adaptability to all weathers
A5: Dimensions L X W X T | B5: 2000 X 800 * 20 | C5: 2000 X 800 * 20 | D5: 2000 X 800 * 20 | E5: 2000 X 800 * 20 | F5: 2000 X 800 * 20
A6: Maximum working Pr. | B6: 10 | C6: 10 | D6: 10 | E6: 10 | F6: 10
A7: Test pressure | B7: 15 | C7: 15 | D7: 15 | E7: 15 | F7: 15
A8: Maximum exposure temp. | B8: 100 | C8: 100 | D8: 100 | E8: 100 | F8: 100
A9: Minimum running temp. | B9: 10 | C9: 10 | D9: 10 | E9: 10 | F9: 10
A10: Qty | B10: 1 | C10: 1 | D10: 2 | E10: 2 | F10: 4
A11: Absorbed power (Average/Max) | B11: 650 | C11: 890 | D11: 890 | E11: 890 | F11: 890
A12: Thermal power (Average/Max) | B12: 3490 | C12: 4750 | D12: 4750 | E12: 4750 | F12: 4750
A13: Electrical support power | B13: 1500 | C13: 1500 | D13: 1500 | E13: 1500 | F13: 1500
A14: Compressor Type | B14: Rotary | C14: Rotary | D14: Rotary | E14: Rotary | F14: Rotary
A15: Compressor Noise Level | B15: 45 | C15: 45 | D15: 45 | E15: 45 | F15: 45
A16: Circulation Pump | B16: Builtin Hot water circualtor Pump | C16: Builtin Hot water circualtor Pump | D16: Builtin Hot water circualtor Pump | E16: Builtin Hot water circualtor Pump | F16: Builtin Hot water circualtor Pump
A17: Net Weight
A18: Cabinet | B18: Stainless Steel / Galvanised Steek | C18: Stainless Steel / Galvanised Steek | D18: Stainless Steel / Galvanised Steek | E18: Stainless Steel / Galvanised Steek | F18: Stainless Steel / Galvanised Steek
A19: Dimension | B19: 500 X 450 X 375 | C19: 500 X 450 X 375 | D19: 500 X 450 X 375 | E19: 500 X 450 X 375 | F19: 500 X 450 X 375
A20: Cooling Fluid * | B20: R134a | C20: R134a | D20: R134a | E20: R134a | F20: R134a
A21: Piping Material | B21: Copper (DHP ISO1337) | C21: Copper (DHP ISO1337) | D21: Copper (DHP ISO1337) | E21: Copper (DHP ISO1337) | F21: Copper (DHP ISO1337)
A22: Line of liquid | B22: 1/4” | C22: 1/4” | D22: 3/8" | E22: 3/8" | F22: 3/8"
A23: Line of aspiration | B23: 3/8” | C23: 3/8” | D23: 1/2" | E23: 1/2" | F23: 1/2"
A24: Volume | B24: 200 | C24: 300 | D24: 300 | E24: 500 | F24: 500
A25: Type of internal Tank | B25: MS with SPL EPOXY enamel Coated | C25: MS with SPL EPOXY enamel Coated | D25: MS with SPL EPOXY enamel Coated | E25: MS with SPL EPOXY enamel Coated | F25: MS with SPL EPOXY enamel Coated
A26: Hydraulic joints | B26: 3/4” Male | 3/4” Male 1/2 Female | 3/4” Female | C26: 3/4” Male | 3/4” Male 1/2 Female | 3/4” Female | D26: 3/4” Male | 3/4” Male 1/2 Female | 3/4” Female | E26: 3/4” Male | 3/4” Male 1/2 Female | 3/4” Female | F26: 3/4” Male | 3/4” Male 1/2 Female | 3/4” Female
A27: Maximum pressure | B27: 7 | C27: 7 | D27: 7 | E27: 7 | F27: 7
A28: Test pressure | B28: 10 | C28: 10 | D28: 10 | E28: 10 | F28: 10
A29: Maximum water temp. | B29: 60 | C29: 60 | D29: 60 | E29: 60 | F29: 60
A30: Water temperature | B30: 55 | C30: 55 | D30: 55 | E30: 55 | F30: 55
A31: Power feed | B31: 230 Single Phase / 50 | C31: 230 Single Phase / 50 | D31: 230 Single Phase / 50 | E31: 230 Single Phase / 50 | F31: 230 Single Phase / 50
A32: Controller | B32: Next Gen PCB controller | C32: Next Gen PCB controller | D32: Next Gen PCB controller | E32: Next Gen PCB controller | F32: Next Gen PCB controller
C37: MODEL_NO
C38: MiNi1-200
C39: MiNi1-300
C40: MiNi2-300
C41: MiNi2-500
C42: MiNi4-500
A47: Model | B47: Material & Finish | C47: Thickness | D47: Protection | E47: Dimensions L X W X T | F47: Maximum working Pr. | G47: Test pressure | H47: Maximum exposure temp. | I47: Minimum running temp. | J47: Qty | K47: Absorbed power (Average/Max) | L47: Thermal power (Average/Max) | M47: Electrical support power | N47: Compressor Type | O47: Compressor Noise Level | P47: Circulation Pump | Q47: Net Weight | R47: Cabinet | S47: Dimension | T47: Cooling Fluid * | U47: Piping Material | V47: Line of liquid | W47: Line of aspiration | X47: Volume | Y47: Type of internal Tank | Z47: Hydraulic joints | AA47: Maximum pressure | AB47: Test pressure | AC47: Maximum water temp. | AD47: Water temperature | AE47: Power feed | AF47: Controller
A48: MiNi1-200 | B48: Powder coated Anodised aluminium Alloy panel | C48: 2mm aluminium for increased mechanical strength | D48: Corrosion resistant and adaptability to all weathers | E48: 2000 X 800 * 20 | F48: 10 | G48: 15 | H48: 100 | I48: 10 | J48: 1 | K48: 650 | L48: 3490 | M48: 1500 | N48: Rotary | O48: 45 | P48: Builtin Hot water circualtor Pump | R48: Stainless Steel / Galvanised Steek | S48: 500 X 450 X 375 | T48: R134a | U48: Copper (DHP ISO1337) | V48: 1/4” | W48: 3/8” | X48: 200 | Y48: MS with SPL EPOXY enamel Coated | Z48: 3/4” Male | 3/4” Male 1/2 Female | 3/4” Female | AA48: 7 | AB48: 10 | AC48: 60 | AD48: 55 | AE48: 230 Single Phase / 50 | AF48: Next Gen PCB controller
A49: MiNi1-300 | B49: Powder coated Anodised aluminium Alloy panel | C49: 2mm aluminium for increased mechanical strength | D49: Corrosion resistant and adaptability to all weathers | E49: 2000 X 800 * 20 | F49: 10 | G49: 15 | H49: 100 | I49: 10 | J49: 1 | K49: 650 | L49: 3490 | M49: 1500 | N49: Rotary | O49: 45 | P49: Builtin Hot water circualtor Pump | R49: Stainless Steel / Galvanised Steek | S49: 500 X 450 X 375 | T49: R134a | U49: Copper (DHP ISO1337) | V49: 1/4” | W49: 3/8” | X49: 300 | Y49: MS with SPL EPOXY enamel Coated | Z49: 3/4” Male | 3/4” Male 1/2 Female | 3/4” Female | AA49: 7 | AB49: 10 | AC49: 60 | AD49: 55 | AE49: 230 Single Phase / 50 | AF49: Next Gen PCB controller
A50: MiNi2-300 | B50: Powder coated Anodised aluminium Alloy panel | C50: 2mm aluminium for increased mechanical strength | D50: Corrosion resistant and adaptability to all weathers | E50: 2000 X 800 * 20 | F50: 10 | G50: 15 | H50: 100 | I50: 10 | J50: 2 | K50: 650 | L50: 3490 | M50: 1500 | N50: Rotary | O50: 45 | P50: Builtin Hot water circualtor Pump | R50: Stainless Steel / Galvanised Steek | S50: 500 X 450 X 375 | T50: R134a | U50: Copper (DHP ISO1337) | V50: 3/8" | W50: 1/2" | X50: 300 | Y50: MS with SPL EPOXY enamel Coated | Z50: 3/4” Male | 3/4” Male 1/2 Female | 3/4” Female | AA50: 7 | AB50: 10 | AC50: 60 | AD50: 55 | AE50: 230 Single Phase / 50 | AF50: Next Gen PCB controller
A51: MiNi2-500 | B51: Powder coated Anodised aluminium Alloy panel | C51: 2mm aluminium for increased mechanical strength | D51: Corrosion resistant and adaptability to all weathers | E51: 2000 X 800 * 20 | F51: 10 | G51: 15 | H51: 100 | I51: 10 | J51: 2 | K51: 890 | L51: 4750 | M51: 1500 | N51: Rotary | O51: 45 | P51: Builtin Hot water circualtor Pump | R51: Stainless Steel / Galvanised Steek | S51: 500 X 450 X 375 | T51: R134a | U51: Copper (DHP ISO1337) | V51: 3/8" | W51: 1/2" | X51: 500 | Y51: MS with SPL EPOXY enamel Coated | Z51: 3/4” Male | 3/4” Male 1/2 Female | 3/4” Female | AA51: 7 | AB51: 10 | AC51: 60 | AD51: 55 | AE51: 230 Single Phase / 50 | AF51: Next Gen PCB controller
A52: MiNi4-500 | B52: Powder coated Anodised aluminium Alloy panel | C52: 2mm aluminium for increased mechanical strength | D52: Corrosion resistant and adaptability to all weathers | E52: 2000 X 800 * 20 | F52: 10 | G52: 15 | H52: 100 | I52: 10 | J52: 4 | K52: 890 | L52: 4750 | M52: 1500 | N52: Rotary | O52: 45 | P52: Builtin Hot water circualtor Pump | R52: Stainless Steel / Galvanised Steek | S52: 500 X 450 X 375 | T52: R134a | U52: Copper (DHP ISO1337) | V52: 3/8" | W52: 1/2" | X52: 500 | Y52: MS with SPL EPOXY enamel Coated | Z52: 3/4” Male | 3/4” Male 1/2 Female | 3/4” Female | AA52: 7 | AB52: 10 | AC52: 60 | AD52: 55 | AE52: 230 Single Phase / 50 | AF52: Next Gen PCB controller
F59: =LEN(B60) -> 198
B60: Vindsol Next Gen Themrodynamic solar heat pump with Single Panel and Control Unit with built in Circulation pump, Model : MiNi1-200, Heat Cap : 3.5Kw Input Power : 0.88Kw , Ref:R134a, 220V/1PH/ 50Hz
B62: Powder coated Anodised aluminium Alloy panel
B63: 2mm aluminium for increased mechanical strength
B64: Corrosion resistant and adaptability to all weathers
B65: 2000 X 800 * 20
B66: 10
B67: 15
B68: 100
B69: 10
B70: 1
B71: 650
B72: 3490
B73: 1500
B74: Rotary
B75: 45
B76: Builtin Hot water circualtor Pump
B78: Stainless Steel / Galvanised Steek
B79: 500 X 450 X 375
B80: R134a
B81: Copper (DHP ISO1337)
B82: 1/4”
B83: 3/8”
B84: 200
B85: MS with Porcelain Blue Glass Lined
B86: 3/4” Male | 3/4” Male 1/2 Female | 3/4” Female
B87: 7
B88: 10
B89: 60
B90: 55
B91: 230 Single Phase / 50
B92: Next Gen PCB controller
